octocat/__init__.py
octocat/octocat.py
octocat-0.4.0.dist-info/DESCRIPTION.rst
octocat-0.4.0.dist-info/METADATA
octocat-0.4.0.dist-info/metadata.json
octocat-0.4.0.dist-info/RECORD
octocat-0.4.0.dist-info/top_level.txt
octocat-0.4.0.dist-info/WHEEL
tests/__init__.py
tests/test_octocat.py
