Metadata-Version: 2.0
Name: octocat
Version: 0.4.0
Summary: UNKNOWN
Home-page: https://github.com/klen/octocat
Author: Kirill Klenov
Author-email: horneds@gmail.com
License: BSD
Keywords: django,flask,sqlalchemy,testing,mock,stub,mongoengine,data
Platform: Any
Classifier: Development Status :: 4 - Beta
Classifier: Intended Audience :: Developers
Classifier: License :: OSI Approved :: BSD License
Classifier: Natural Language :: English
Classifier: Natural Language :: Russian
Classifier: Operating System :: OS Independent
Classifier: Programming Language :: Python :: 2
Classifier: Programming Language :: Python :: 3
Classifier: Programming Language :: Python
Classifier: Topic :: Software Development :: Libraries :: Python Modules
Classifier: Topic :: Software Development :: Testing
Classifier: Topic :: Utilities
Requires-Dist: requests (>=2.3.0)
Requires-Dist: requests-cache (>=0.4.5)
